limiters/__init__.py
limiters/base.py
limiters/exceptions.py
limiters/py.typed
limiters/semaphore.lua
limiters/semaphore.py
limiters/token_bucket.lua
limiters/token_bucket.py
redis_rate_limiters-0.4.5.dist-info/LICENSE
redis_rate_limiters-0.4.5.dist-info/METADATA
redis_rate_limiters-0.4.5.dist-info/WHEEL
redis_rate_limiters-0.4.5.dist-info/RECORD
