Metadata-Version: 2.1
Name: redis-rate-limiters
Version: 0.4.5
Summary: Distributed rate limiters
Home-page: https://github.com/otovo/redis-rate-limiters
License: BSD-4-Clause
Keywords: async,sync,rate,limiting,limiters
Author: Sondre Lillebø Gundersen
Author-email: sondrelg@live.no
Requires-Python: >=3.11,<4.0
Classifier: Development Status :: 4 - Beta
Classifier: Environment :: Web Environment
Classifier: Intended Audience :: Developers
Classifier: License :: OSI Approved :: BSD License
Classifier: License :: Other/Proprietary License
Classifier: Operating System :: OS Independent
Classifier: Programming Language :: Python
Classifier: Programming Language :: Python :: 3
Classifier: Programming Language :: Python :: 3.11
Classifier: Programming Language :: Python :: 3.12
Classifier: Topic :: Internet :: WWW/HTTP
Classifier: Topic :: Internet :: WWW/HTTP :: Dynamic Content
Classifier: Topic :: Software Development
Classifier: Topic :: Software Development :: Libraries
Classifier: Topic :: Software Development :: Libraries :: Application Frameworks
Classifier: Topic :: Software Development :: Libraries :: Python Modules
Requires-Dist: pydantic (<2)
Requires-Dist: redis (>4.2)
Project-URL: Repository, https://github.com/otovo/redis-rate-limiters
